django_asservio_core/__init__.py
django_asservio_core/settings.py
django_asservio_core/urls.py
django_asservio_core/management/__init__.py
django_asservio_core/management/commands/__init__.py
django_asservio_core/management/commands/seed_world_data.py
django_asservio_core/models/__init__.py
django_asservio_core/models/audit.py
django_asservio_core/models/dictionaries.py
django_asservio_core/models/general.py
django_asservio_core/tests/__init__.py
django_asservio_core/tests/conftest.py
django_asservio_core/tests/models.py
django_asservio_core/tests/test_commands.py
django_asservio_core/tests/test_dictionaries.py
django_asservio_core/tests/urls.py
django_asservio_core/tests/utils.py
django_asservio_core/utils/__init__.py
django_asservio_core/utils/general_utils.py
django_asservio_core/utils/utils.py
django_asservio_core-0.1.0.dist-info/DESCRIPTION.rst
django_asservio_core-0.1.0.dist-info/METADATA
django_asservio_core-0.1.0.dist-info/RECORD
django_asservio_core-0.1.0.dist-info/WHEEL
django_asservio_core-0.1.0.dist-info/metadata.json
django_asservio_core-0.1.0.dist-info/top_level.txt
