Metadata-Version: 2.0
Name: django-asservio-core
Version: 0.1.0
Summary: Django general purpose lib used in Asservio.
Home-page: http://django-asservio-core.readthedocs.org
Author: Aleksey, Alexander Osin
Author-email: quant@apologist.io, alexandre.osin@gmail.com
License: Unlicense
Platform: UNKNOWN
Classifier: Development Status :: 2 - Pre-Alpha
Classifier: Environment :: Web Environment
Classifier: Framework :: Django
Classifier: Intended Audience :: Developers
Classifier: Operating System :: OS Independent
Classifier: Programming Language :: Python
Classifier: Programming Language :: Python :: 3.5
Classifier: Programming Language :: Python :: 3.6
